carbgremover/__init__.py
carbgremover/external_model.py
carbgremover/internal_model.py
carbgremover/images/car1.jpg
carbgremover/images/car2.jpg
carbgremover/images/rescar1.jpg
carbgremover/images/rescar2.jpg
car_segmentation-1.0.0.dist-info/METADATA
car_segmentation-1.0.0.dist-info/WHEEL
car_segmentation-1.0.0.dist-info/top_level.txt
car_segmentation-1.0.0.dist-info/RECORD
